README.md
setup.py
Flask_Matomo_D.egg-info/PKG-INFO
Flask_Matomo_D.egg-info/SOURCES.txt
Flask_Matomo_D.egg-info/dependency_links.txt
Flask_Matomo_D.egg-info/not-zip-safe
Flask_Matomo_D.egg-info/requires.txt
Flask_Matomo_D.egg-info/top_level.txt
flask_matomo/__init__.py
flask_matomo/core.py