Metadata-Version: 2.1
Name: Flask-Matomo-D
Version: 0.0.3
Summary: Track requests to your Flask website with Matomo 
Home-page: https://github.com/firefresh/flask-matomo-d
Author: Demetrio Dowbnac
Author-email: demetriodowbnac@gmail.com
License: UNKNOWN
Platform: UNKNOWN
Classifier: Environment :: Web Environment
Classifier: Intended Audience :: Developers
Classifier: License :: OSI Approved :: MIT License
Classifier: Operating System :: OS Independent
Classifier: Programming Language :: Python :: 2.7
Classifier: Programming Language :: Python :: 3
Classifier: Topic :: Internet :: WWW/HTTP :: Dynamic Content
Classifier: Topic :: Software Development :: Libraries :: Python Modules
